vclean/__init__.py
vclean/cli.py
vclean/db/__init__.py
vclean/db/single_pfam.txt
vclean/db/single_pfam_099.txt
vclean/db/unique_single_pfam.txt
vclean/models/best_lgb_model_fold0.txt
vclean/models/best_lgb_model_fold1.txt
vclean/models/best_lgb_model_fold2.txt
vclean/models/best_lgb_model_fold3.txt
vclean/models/best_lgb_model_fold4.txt
vclean/models/best_lgb_model_v1.3.2.pickle
vclean/modules/__init__.py
vclean/modules/checkv.py
vclean/modules/cli.py
vclean/modules/codon.py
vclean/modules/count_redundant_protein.py
vclean/modules/download_database_for_cli.py
vclean/modules/estimate_simu_contami.py
vclean/modules/gc.py
vclean/modules/lgb_model.py
vclean/modules/penta_jelly.py
vclean/modules/read_table.py
vclean/modules/run_for_cli.py
vclean/modules/seqkit.py
vclean/modules/singlecopy_counts.py
vclean/modules/tetra_jelly.py
vclean-0.2.1.dist-info/entry_points.txt
vclean-0.2.1.dist-info/LICENSE
vclean-0.2.1.dist-info/WHEEL
vclean-0.2.1.dist-info/METADATA
vclean-0.2.1.dist-info/RECORD
