Metadata-Version: 2.1
Name: vclean
Version: 0.2.1
Summary: vClean: Assessing the contamination of viral genomes
Author-email: Ryota Wagatsuma <cold_bz@ruri.waseda.jp>
Requires-Python: ==3.9
Requires-Dist: pandas
Requires-Dist: numpy
Requires-Dist: matplotlib
Requires-Dist: seaborn
Requires-Dist: scikit-learn
Requires-Dist: lightgbm
Requires-Dist: biopython
Project-URL: Home, https://github.com/TsumaR/vclean
Project-URL: Source, https://github.com/TsumaR/vclean
